Workbook

Sheet Executive Summary
B1: MUSE — BOARDROOM INVESTOR / MARKET AUDIT
B2: Prepared by Claude, in the role of outside investor / inspector / auditor
B4: Methodology note: this is a qualitative expert-opinion audit grounded in Muse's own internal strategy/product documentation (MUSE_OVERVIEW.md, MUSE_MONEY.md, MUSE_DEMOGRAPHICS_DEMAND.md, MUSE_GAPS_ADJUSTMENTS.md, MUSE_CLAUDE_CRITIQUE.md, STRATEGY.md, COMPETITIVE_UX_REPORT.md) plus this engagement's own live product testing — NOT real financial statements, market research, or third-party diligence. It is opinion, not licensed investment or legal advice, and should not be the sole basis for any funding, valuation, or go/no-go decision.
B5: Structure: 10 categories x 10 subcategories = 100 independently-reasoned scores (see 'Category Scores' and 'Full Rubric' tabs). Each subcategory score is itself the average of 10 standard evaluation lenses (Strength, Differentiation, Evidence, User Value, Revenue Relevance, Risk, Scalability, Cost-to-Fix, Timing, Investor Optics) — decomposed mechanically per category-level patterns rather than 1,000 separately hand-written judgments, which would have manufactured false precision at this stage of the company. The 100 subcategory scores are the real analysis; the full 1,000-cell grid is there for anyone who wants to see how each one breaks down.
B7: THE HEADLINE VERDICT
B8: Overall score: see 'Category Scores' tab, cell C12 (auto-calculated, currently ~6.0/10). That number lines up almost exactly with the team's own internal verdict: 'works, not platinum.' This is a genuinely well-conceived, well-documented, honestly self-critical product with real differentiated safety/escrow engineering and a rare pre-launch distribution asset (FD Photo Studio + a running 3-city Mixers community) — sitting on top of zero revenue, zero measured users, a live positioning tension the product hasn't yet resolved visually, and several compliance items that are built but not yet legally or regulatorily cleared.
B10: THE GOOD
B11: • The trust/transaction wedge is real and defensible on paper — verification + consent + escrow + check-ins is a genuine, differentiated moat nobody named as a competitor fully owns.
B12: • FD Photo Studio + LA/NYC/Chicago Mixers is a rare, pre-launch, real-world distribution and supply advantage most marketplaces never get before day one.
B13: • The internal documentation discipline (7+ consistent strategy docs, an honest gaps list, a competitive field report) is more mature than most funded seed-stage startups produce.
B14: • The payment engineering (Stripe Connect manual-capture escrow, auto-capture safety cron, refund/dispute workflow) is genuinely production-grade, not demo-grade.
B15: • Execution velocity is fast and iterative — bugs get found, fixed, tested, and shipped within hours across this engagement.
... B41: As an outside investor/auditor: this is a fundable STORY at the earliest possible stage — a real wedge, a real founder-market fit, a rare distribution asset, and unusually honest internal self-assessment — but it is not yet a fundable BUSINESS. The very next milestones that would change this verdict are exactly the ones the team has already named for itself: seed real supply in one city, close the host-onboarding gap, instrument transactions (not signups), clear NCMEC + attorney review, and resolve the dating-app visual tension before it reaches an industry buyer's screen. None of these are hard technically. All of them are prerequisites, not nice-to-haves, before this becomes a number an investor could actually underwrite.

Sheet Full Rubric (1000)
A1: Category | B1: Subcategory | C1: Subcategory Score (avg of lenses) | D1: Strength as-is | E1: Differentiation | F1: Evidence/Confidence | G1: User Value/Impact | H1: Revenue Relevance | I1: Risk Exposure (10=low risk) | J1: Scalability | K1: Cost/Effort to Fix (10=cheap) | L1: Trend/Timing Alignment | M1: Investor Optics | N1: Note (rationale)
A2: 1. Concept, Thesis & Positioning | B2: Core thesis clarity | C2: =AVERAGE(D2:M2) -> 9.4 | D2: 10 | E2: 10 | F2: 8 | G2: 10 | H2: 9 | I2: 9 | J2: 9 | K2: 9 | L2: 10 | M2: 10 | N2: Unusually clear, consistent one-liner across every doc: 'the verified, consented, protected marketplace for creative shoots.'
A3: 1. Concept, Thesis & Positioning | B3: Problem-solution fit | C3: =AVERAGE(D3:M3) -> 8.5 | D3: 9 | E3: 10 | F3: 7 | G3: 9 | H3: 8 | I3: 8 | J3: 8 | K3: 8 | L3: 9 | M3: 9 | N3: The FB-groups/DM/Venmo problem is real and specific; the solution maps to it directly, not abstractly.
A4: 1. Concept, Thesis & Positioning | B4: Brand & emotional positioning | C4: =AVERAGE(D4:M4) -> 8.5 | D4: 9 | E4: 10 | F4: 7 | G4: 9 | H4: 8 | I4: 8 | J4: 8 | K4: 8 | L4: 9 | M4: 9 | N4: 'Be seen, be made into art' is a genuine dignity-play differentiator vs. Fiverr/Upwork's efficiency framing.
A5: 1. Concept, Thesis & Positioning | B5: Naming & identity ('Muse') | C5: =AVERAGE(D5:M5) -> 7.5 | D5: 8 | E5: 9 | F5: 6 | G5: 8 | H5: 7 | I5: 7 | J5: 7 | K5: 7 | L5: 8 | M5: 8 | N5: Evocative, but a common word — thin ground for trademark/SEO defensibility.
A6: 1. Concept, Thesis & Positioning | B6: Category definition | C6: =AVERAGE(D6:M6) -> 7.5 | D6: 8 | E6: 9 | F6: 6 | G6: 8 | H6: 7 | I6: 7 | J6: 7 | K6: 7 | L6: 8 | M6: 8 | N6: Clear on paper as 'not dating, not a job board' — but see 1.6.
A7: 1. Concept, Thesis & Positioning | B7: Positioning discipline vs. dating-app drift | C7: =AVERAGE(D7:M7) -> 5.5 | D7: 6 | E7: 7 | F7: 4 | G7: 6 | H7: 5 | I7: 5 | J7: 5 | K7: 5 | L7: 6 | M7: 6 | N7: Stated discipline is strong; the live UI (swipe cards, %-match badges, heart/nope buttons, zodiac) visually contradicts it — the docs' own #1 self-flagged risk, confirmed live.
A8: 1. Concept, Thesis & Positioning | B8: Two-sided duality insight | C8: =AVERAGE(D8:M8) -> 8.5 | D8: 9 | E8: 10 | F8: 7 | G8: 9 | H8: 8 | I8: 8 | J8: 8 | K8: 8 | L8: 9 | M8: 9 | N8: Genuinely clever structural idea: supply and demand are the same people choosing each other.
A9: 1. Concept, Thesis & Positioning | B9: Vibe/personality matching (zodiac/MBTI) | C9: =AVERAGE(D9:M9) -> 4.5 | D9: 5 | E9: 6 | F9: 3 | G9: 5 | H9: 4 | I9: 4 | J9: 4 | K9: 4 | L9: 5 | M9: 5 | N9: Repeatedly self-flagged as the single biggest strategic tension — charming for retail creatives, actively undermines industry-buyer trust.
A10: 1. Concept, Thesis & Positioning | B10: Narrative consistency across docs | C10: =AVERAGE(D10:M10) -> 9.4 | D10: 10 | E10: 10 | F10: 8 | G10: 10 | H10: 9 | I10: 9 | J10: 9 | K10: 9 | L10: 10 | M10: 10 | N10: Rare internal alignment across 7+ strategy documents — a real discipline strength.
A11: 1. Concept, Thesis & Positioning | B11: Long-term vision (trust-data-as-credit-bureau) | C11: =AVERAGE(D11:M11) -> 6.5 | D11: 7 | E11: 8 | F11: 5 | G11: 7 | H11: 6 | I11: 6 | J11: 6 | K11: 6 | L11: 7 | M11: 7 | N11: Bold and interesting, but self-flagged FCRA exposure if pursued carelessly; correctly sequenced as 'not now.'
A12: 2. Market Opportunity & Demand | B12: TAM/SAM/SOM definition | C12: =AVERAGE(D12:M12) -> 2.9 | D12: 3 | E12: 3 | F12: 1 | G12: 3 | H12: 4 | I12: 2 | J12: 3 | K12: 2 | L12: 5 | M12: 3 | N12: No market sizing exists anywhere in the reviewed docs. STRATEGY.md itself says any figure at 0 users/0 revenue is speculation.
A13: 2. Market Opportunity & Demand | B13: Informal market as proof of demand | C13: =AVERAGE(D13:M13) -> 7.9 | D13: 8 | E13: 8 | F13: 6 | G13: 8 | H13: 9 | I13: 7 | J13: 8 | K13: 7 | L13: 10 | M13: 8 | N13: FB groups/DMs/Venmo 'at massive scale' is a genuinely strong informal-demand signal — Craigslist/Airbnb-style whitespace.
... A101: 10. Risk, Governance & Exit Readiness | B101: Exit optionality & timeline realism | C101: =AVERAGE(D101:M101) -> 4.3 | D101: 5 | E101: 5 | F101: 5 | G101: 4 | H101: 4 | I101: 3 | J101: 4 | K101: 4 | L101: 5 | M101: 4 | N101: Named, plausible acquirer categories exist; the docs are honest that no real timeline or figure can be derived yet — appropriately cautious rather than inflated.

Sheet Category Scores
A1: # | B1: Category | C1: Category Score (avg of 10 subcats) | D1: Verdict
A2: 1 | B2: 1. Concept, Thesis & Positioning | C2: =AVERAGE('Full Rubric (1000)'!C2:C11) -> 7.58 | D2: A genuinely strong, well-articulated thesis undercut by one unresolved tension: the live product still visually reads like the dating app the strategy explicitly says to avoid.
A3: 2 | B3: 2. Market Opportunity & Demand | C3: =AVERAGE('Full Rubric (1000)'!C12:C21) -> 6.19 | D3: Real informal-market proof and a rare distribution asset (FD Mixers) — but no sizing, no third-party validation. Demand for the CATEGORY is proven; demand for MUSE is not yet.
A4: 3 | B4: 3. Business Model & Monetization | C4: =AVERAGE('Full Rubric (1000)'!C22:C31) -> 6.49 | D4: A mature, multi-stream, well-engineered payment model on paper — with zero unit-economics evidence and a self-identified host-onboarding bottleneck sitting on top of the entire revenue engine.
A5: 4 | B5: 4. Product Experience & Value Delivery | C5: =AVERAGE('Full Rubric (1000)'!C32:C41) -> 6.49 | D5: The safety/transaction machinery is genuinely best-in-class. The visual polish is not — this one engagement alone found four live, user-visible UI bugs on a single primary screen.
A6: 5 | B6: 5. Competitive Positioning & Moat | C6: =AVERAGE('Full Rubric (1000)'!C42:C51) -> 6.5 | D6: Smart, correctly-scoped competitive reads across the board. The moat is real in theory but doesn't exist yet — it only accrues once transactions actually run at volume.
A7: 6 | B7: 6. Trust, Safety & Compliance | C7: =AVERAGE('Full Rubric (1000)'!C52:C61) -> 7.07 | D7: The best category in the whole audit for shipped, working, differentiated features. Two real, self-flagged open items (NCMEC approval, legal sign-off) keep it from a higher score.
A8: 7 | B8: 7. Go-to-Market & Growth | C8: =AVERAGE('Full Rubric (1000)'!C62:C71) -> 6.2 | D8: A textbook seed-stage GTM plan riding real offline distribution — weakened by zero funnel instrumentation and two aspirational studio partnerships presented as if they were real.
A9: 8 | B9: 8. Team, Founder & Execution Readiness | C9: =AVERAGE('Full Rubric (1000)'!C72:C81) -> 6.6 | D9: Outstanding founder-market fit and documentation discipline, fast iteration — offset by real technical debt, a live bug-density signal, and a classic single-founder scaling risk.
A10: 9 | B10: 9. Financial & Investment Potential | C10: =AVERAGE('Full Rubric (1000)'!C82:C91) -> 3.43 | D10: The weakest category, honestly: $0 revenue, $0 users, no burn/runway data, no comparable exits beyond a directional reference. Correctly, the team's own docs don't oversell this either.
A11: 10 | B11: 10. Risk, Governance & Exit Readiness | C11: =AVERAGE('Full Rubric (1000)'!C92:C101) -> 3.6 | D11: A cluster of real, named, currently-open risks (regulatory, platform, reputational, scaling, key-person) — balanced by genuinely strong documentation and governance discipline.
B12: OVERALL AUDIT SCORE | C12: =AVERAGE(C2:C11) -> 6.015
